<options>

<eanalyze help="Histogram and correlation function of site energies and pair energy differences" section="sec:eanalyze">

	<resolution_sites help="Bin size for site energy histogram" unit="eV">0.1</resolution_sites>
	<resolution_pairs help="Bin size for pair energy histogram" unit="eV">0.1</resolution_pairs>
	<resolution_space help="Bin size for site energy correlation" unit="eV">0.1</resolution_space>
	<states help="?">e h s t</states>
	<!--do_atomic_xyze help="?">0</do_atomic_xyze-->
	<!--atomic_first>1</atomic_first-->
	<!--atomic_last>-1</atomic_last-->

</eanalyze>

</options>
