<eanalyze>
  
	<description>Site energy histogram, pair energy histogram, normalized site energy correlation function</description>

	<sectionlabel>eanalyze</sectionlabel>

        <item>
                <name>RESOLUTION_SITES</name>
                <description>Bin size for site energy histogram</description>
        </item>
	<item>
		<name>RESOLUTION_PAIRS</name>
		<description>Bin size for pair energy histogram</description>
	</item>

	<item>
		<name>RESOLUTION_SPACE</name>
		<description>Bin size for site energy correlation</description>
	</item>


</eanalyze>
